AUTHORS
CONTRIBUTORS
LICENSE
MANIFEST.in
README.rst
setup.py
django_elasticmodels.egg-info/PKG-INFO
django_elasticmodels.egg-info/SOURCES.txt
django_elasticmodels.egg-info/dependency_links.txt
django_elasticmodels.egg-info/not-zip-safe
django_elasticmodels.egg-info/requires.txt
django_elasticmodels.egg-info/top_level.txt
elasticmodels/__init__.py
elasticmodels/_version.py
elasticmodels/index.py
elasticmodels/settings.py
elasticmodels/management/__init__.py
elasticmodels/management/commands/__init__.py
elasticmodels/management/commands/create_indexes.py