Metadata-Version: 1.0
Name: django-elasticmodels
Version: 1.0
Summary: A tool to map Django models to ElasticSearch mappings
Home-page: https://bitbucket.com/jvennik/django-elasticmodels
Author: Jos Vennik
Author-email: josvennik@gmail.com
License:    Copyright 2011-2013 Jos Vennik <josvennik@gmail.com>
